plainflow/__init__.py
plainflow/client.py
plainflow/consumer.py
plainflow/request.py
plainflow/utils.py
plainflow/version.py
plainflow/test/__init__.py
plainflow/test/client.py
plainflow/test/consumer.py
plainflow/test/module.py
plainflow/test/request.py
plainflow/test/utils.py
plainflow-1.2.8.post1.dist-info/DESCRIPTION.rst
plainflow-1.2.8.post1.dist-info/METADATA
plainflow-1.2.8.post1.dist-info/RECORD
plainflow-1.2.8.post1.dist-info/WHEEL
plainflow-1.2.8.post1.dist-info/metadata.json
plainflow-1.2.8.post1.dist-info/top_level.txt
